[
  {
    "Political affiliation": "Bloc Québécois",
    "N.L. Percentage of Valid Votes": 0,
    "P.E.I. Percentage of Valid Votes": 0,
    "N.S. Percentage of Valid Votes": 0,
    "N.B. Percentage of Valid Votes": 0,
    "Que. Percentage of Valid Votes": 48.9,
    "Ont. Percentage of Valid Votes": 0,
    "Man. Percentage of Valid Votes": 0,
    "Sask. Percentage of Valid Votes": 0,
    "Alta. Percentage of Valid Votes": 0,
    "B.C. Percentage of Valid Votes": 0,
    "Y.T. Percentage of Valid Votes": 0,
    "N.W.T. Percentage of Valid Votes": 0,
    "Nun. Percentage of Valid Votes": 0,
    "Total": 12.39
  },
  {
    "Political affiliation": "Canadian Action Party",
    "N.L. Percentage of Valid Votes": 0,
    "P.E.I. Percentage of Valid Votes": 0,
    "N.S. Percentage of Valid Votes": 0,
    "N.B. Percentage of Valid Votes": 0.1,
    "Que. Percentage of Valid Votes": 0,
    "Ont. Percentage of Valid Votes": 0,
    "Man. Percentage of Valid Votes": 0,
    "Sask. Percentage of Valid Votes": 0,
    "Alta. Percentage of Valid Votes": 0.1,
    "B.C. Percentage of Valid Votes": 0.3,
    "Y.T. Percentage of Valid Votes": 0,
    "N.W.T. Percentage of Valid Votes": 0,
    "Nun. Percentage of Valid Votes": 0,
    "Total": 0.06
  },
  {
    "Political affiliation": "Christian Heritage Party",
    "N.L. Percentage of Valid Votes": 0,
    "P.E.I. Percentage of Valid Votes": 0.1,
    "N.S. Percentage of Valid Votes": 0.1,
    "N.B. Percentage of Valid Votes": 0,
    "Que. Percentage of Valid Votes": 0,
    "Ont. Percentage of Valid Votes": 0.5,
    "Man. Percentage of Valid Votes": 0.9,
    "Sask. Percentage of Valid Votes": 0.3,
    "Alta. Percentage of Valid Votes": 0.2,
    "B.C. Percentage of Valid Votes": 0.3,
    "Y.T. Percentage of Valid Votes": 0.8,
    "N.W.T. Percentage of Valid Votes": 0,
    "Nun. Percentage of Valid Votes": 0,
    "Total": 0.3
  },
  {
    "Political affiliation": "Communist Party of Canada",
    "N.L. Percentage of Valid Votes": 0,
    "P.E.I. Percentage of Valid Votes": 0,
    "N.S. Percentage of Valid Votes": 0,
    "N.B. Percentage of Valid Votes": 0,
    "Que. Percentage of Valid Votes": 0,
    "Ont. Percentage of Valid Votes": 0,
    "Man. Percentage of Valid Votes": 0.2,
    "Sask. Percentage of Valid Votes": 0,
    "Alta. Percentage of Valid Votes": 0,
    "B.C. Percentage of Valid Votes": 0.1,
    "Y.T. Percentage of Valid Votes": 0,
    "N.W.T. Percentage of Valid Votes": 0,
    "Nun. Percentage of Valid Votes": 0,
    "Total": 0.03
  },
  {
    "Political affiliation": "Conservative Party of Canada",
    "N.L. Percentage of Valid Votes": 32.3,
    "P.E.I. Percentage of Valid Votes": 30.7,
    "N.S. Percentage of Valid Votes": 28,
    "N.B. Percentage of Valid Votes": 31.1,
    "Que. Percentage of Valid Votes": 8.8,
    "Ont. Percentage of Valid Votes": 31.5,
    "Man. Percentage of Valid Votes": 39.1,
    "Sask. Percentage of Valid Votes": 41.8,
    "Alta. Percentage of Valid Votes": 61.7,
    "B.C. Percentage of Valid Votes": 36.3,
    "Y.T. Percentage of Valid Votes": 20.9,
    "N.W.T. Percentage of Valid Votes": 17.2,
    "Nun. Percentage of Valid Votes": 14.4,
    "Total": 29.63
  },
  {
    "Political affiliation": "Green Party of Canada",
    "N.L. Percentage of Valid Votes": 1.6,
    "P.E.I. Percentage of Valid Votes": 4.2,
    "N.S. Percentage of Valid Votes": 3.3,
    "N.B. Percentage of Valid Votes": 3.4,
    "Que. Percentage of Valid Votes": 3.2,
    "Ont. Percentage of Valid Votes": 4.4,
    "Man. Percentage of Valid Votes": 2.7,
    "Sask. Percentage of Valid Votes": 2.7,
    "Alta. Percentage of Valid Votes": 6.1,
    "B.C. Percentage of Valid Votes": 6.3,
    "Y.T. Percentage of Valid Votes": 4.6,
    "N.W.T. Percentage of Valid Votes": 4.3,
    "Nun. Percentage of Valid Votes": 3.3,
    "Total": 4.29
  },
  {
    "Political affiliation": "Liberal Party of Canada",
    "N.L. Percentage of Valid Votes": 48,
    "P.E.I. Percentage of Valid Votes": 52.5,
    "N.S. Percentage of Valid Votes": 39.7,
    "N.B. Percentage of Valid Votes": 44.6,
    "Que. Percentage of Valid Votes": 33.9,
    "Ont. Percentage of Valid Votes": 44.7,
    "Man. Percentage of Valid Votes": 33.2,
    "Sask. Percentage of Valid Votes": 27.2,
    "Alta. Percentage of Valid Votes": 22,
    "B.C. Percentage of Valid Votes": 28.6,
    "Y.T. Percentage of Valid Votes": 45.7,
    "N.W.T. Percentage of Valid Votes": 39.4,
    "Nun. Percentage of Valid Votes": 51.3,
    "Total": 36.73
  },
  {
    "Political affiliation": "Libertarian Party of Canada",
    "N.L. Percentage of Valid Votes": 0,
    "P.E.I. Percentage of Valid Votes": 0,
    "N.S. Percentage of Valid Votes": 0,
    "N.B. Percentage of Valid Votes": 0,
    "Que. Percentage of Valid Votes": 0,
    "Ont. Percentage of Valid Votes": 0,
    "Man. Percentage of Valid Votes": 0,
    "Sask. Percentage of Valid Votes": 0,
    "Alta. Percentage of Valid Votes": 0,
    "B.C. Percentage of Valid Votes": 0.1,
    "Y.T. Percentage of Valid Votes": 0,
    "N.W.T. Percentage of Valid Votes": 0,
    "Nun. Percentage of Valid Votes": 0,
    "Total": 0.01
  },
  {
    "Political affiliation": "Marijuana Party",
    "N.L. Percentage of Valid Votes": 0,
    "P.E.I. Percentage of Valid Votes": 0,
    "N.S. Percentage of Valid Votes": 0.1,
    "N.B. Percentage of Valid Votes": 0.1,
    "Que. Percentage of Valid Votes": 0.4,
    "Ont. Percentage of Valid Votes": 0.2,
    "Man. Percentage of Valid Votes": 0.4,
    "Sask. Percentage of Valid Votes": 0,
    "Alta. Percentage of Valid Votes": 0.2,
    "B.C. Percentage of Valid Votes": 0.2,
    "Y.T. Percentage of Valid Votes": 2.4,
    "N.W.T. Percentage of Valid Votes": 0,
    "Nun. Percentage of Valid Votes": 0,
    "Total": 0.25
  },
  {
    "Political affiliation": "Marxist-Leninist Party of Canada",
    "N.L. Percentage of Valid Votes": 0,
    "P.E.I. Percentage of Valid Votes": 0,
    "N.S. Percentage of Valid Votes": 0,
    "N.B. Percentage of Valid Votes": 0,
    "Que. Percentage of Valid Votes": 0.1,
    "Ont. Percentage of Valid Votes": 0.1,
    "Man. Percentage of Valid Votes": 0,
    "Sask. Percentage of Valid Votes": 0,
    "Alta. Percentage of Valid Votes": 0,
    "B.C. Percentage of Valid Votes": 0.1,
    "Y.T. Percentage of Valid Votes": 0,
    "N.W.T. Percentage of Valid Votes": 0,
    "Nun. Percentage of Valid Votes": 0,
    "Total": 0.06
  },
  {
    "Political affiliation": "New Democratic Party",
    "N.L. Percentage of Valid Votes": 17.5,
    "P.E.I. Percentage of Valid Votes": 12.5,
    "N.S. Percentage of Valid Votes": 28.4,
    "N.B. Percentage of Valid Votes": 20.6,
    "Que. Percentage of Valid Votes": 4.6,
    "Ont. Percentage of Valid Votes": 18.1,
    "Man. Percentage of Valid Votes": 23.5,
    "Sask. Percentage of Valid Votes": 23.4,
    "Alta. Percentage of Valid Votes": 9.5,
    "B.C. Percentage of Valid Votes": 26.6,
    "Y.T. Percentage of Valid Votes": 25.7,
    "N.W.T. Percentage of Valid Votes": 39.1,
    "Nun. Percentage of Valid Votes": 15.2,
    "Total": 15.68
  },
  {
    "Political affiliation": "Progressive Canadian Party",
    "N.L. Percentage of Valid Votes": 0,
    "P.E.I. Percentage of Valid Votes": 0,
    "N.S. Percentage of Valid Votes": 0.3,
    "N.B. Percentage of Valid Votes": 0,
    "Que. Percentage of Valid Votes": 0,
    "Ont. Percentage of Valid Votes": 0.2,
    "Man. Percentage of Valid Votes": 0,
    "Sask. Percentage of Valid Votes": 0,
    "Alta. Percentage of Valid Votes": 0,
    "B.C. Percentage of Valid Votes": 0,
    "Y.T. Percentage of Valid Votes": 0,
    "N.W.T. Percentage of Valid Votes": 0,
    "Nun. Percentage of Valid Votes": 0,
    "Total": 0.08
  },
  {
    "Political affiliation": "Independent",
    "N.L. Percentage of Valid Votes": 0.6,
    "P.E.I. Percentage of Valid Votes": 0,
    "N.S. Percentage of Valid Votes": 0.1,
    "N.B. Percentage of Valid Votes": 0.2,
    "Que. Percentage of Valid Votes": 0.1,
    "Ont. Percentage of Valid Votes": 0.3,
    "Man. Percentage of Valid Votes": 0,
    "Sask. Percentage of Valid Votes": 4.6,
    "Alta. Percentage of Valid Votes": 0,
    "B.C. Percentage of Valid Votes": 0.3,
    "Y.T. Percentage of Valid Votes": 0,
    "N.W.T. Percentage of Valid Votes": 0,
    "Nun. Percentage of Valid Votes": 15.7,
    "Total": 0.35
  },
  {
    "Political affiliation": "No Affiliation",
    "N.L. Percentage of Valid Votes": 0,
    "P.E.I. Percentage of Valid Votes": 0,
    "N.S. Percentage of Valid Votes": 0,
    "N.B. Percentage of Valid Votes": 0,
    "Que. Percentage of Valid Votes": 0,
    "Ont. Percentage of Valid Votes": 0,
    "Man. Percentage of Valid Votes": 0,
    "Sask. Percentage of Valid Votes": 0,
    "Alta. Percentage of Valid Votes": 0,
    "B.C. Percentage of Valid Votes": 1,
    "Y.T. Percentage of Valid Votes": 0,
    "N.W.T. Percentage of Valid Votes": 0,
    "Nun. Percentage of Valid Votes": 0,
    "Total": 0.13
  }
]